plover_vlc_commands.py
plover_vlc_commands-0.6.6.dist-info/METADATA
plover_vlc_commands-0.6.6.dist-info/WHEEL
plover_vlc_commands-0.6.6.dist-info/entry_points.txt
plover_vlc_commands-0.6.6.dist-info/top_level.txt
plover_vlc_commands-0.6.6.dist-info/zip-safe
plover_vlc_commands-0.6.6.dist-info/RECORD
